camundactl/__init__.py
camundactl/__main__.py
camundactl/client.py
camundactl/client_test.py
camundactl/cmd/__init__.py
camundactl/cmd/base.py
camundactl/cmd/base_test.py
camundactl/cmd/config.py
camundactl/cmd/helpers.py
camundactl/cmd/info.py
camundactl/cmd/openapi/__init__.py
camundactl/cmd/openapi/base.py
camundactl/cmd/openapi/factory.py
camundactl/cmd/openapi/factory_test.py
camundactl/cmd/openapi/openapi_specs/__init__.py
camundactl/cmd/openapi/openapi_specs/openapi-7.13.0.json
camundactl/cmd/openapi/openapi_specs/openapi-7.14.0.json
camundactl/cmd/openapi/openapi_specs/openapi-7.15.0.json
camundactl/cmd/openapi/openapi_specs/openapi-7.16.0.json
camundactl/cmd/openapi/openapi_specs/openapi-latest.json
camundactl/cmd/openapi/openapi_specs/openapi.json
camundactl/cmd/openapi/schema.py
camundactl/cmd/process_instance.py
camundactl/config.py
camundactl/output/__init__.py
camundactl/output/base.py
camundactl/output/base_test.py
camundactl/output/decorator.py
camundactl/output/decorator_test.py
camundactl/output/json.py
camundactl/output/json_test.py
camundactl/output/jsonpath.py
camundactl/output/jsonpath_test.py
camundactl/output/raw.py
camundactl/output/table.py
camundactl/output/table_test.py
camundactl/output/template.py
camundactl/utils.py
camundactl-0.1.0a4.dist-info/entry_points.txt
camundactl-0.1.0a4.dist-info/LICENSE
camundactl-0.1.0a4.dist-info/WHEEL
camundactl-0.1.0a4.dist-info/METADATA
camundactl-0.1.0a4.dist-info/RECORD
